span_panel/__init__.py
span_panel/__main__.py
span_panel/api.py
span_panel/client_README.md
span_panel/exceptions.py
span_panel/cli/__init__.py
span_panel/cli/base.py
span_panel/cli/circuits.py
span_panel/cli/panel.py
span_panel/cli/storage.py
span_panel/client/__init__.py
span_panel/client/api_client.py
span_panel/client/api_response.py
span_panel/client/configuration.py
span_panel/client/exceptions.py
span_panel/client/rest.py
span_panel/client/api/__init__.py
span_panel/client/api/default_api.py
span_panel/client/docs/AllowedEndpointGroups.md
span_panel/client/docs/AuthIn.md
span_panel/client/docs/AuthOut.md
span_panel/client/docs/BatteryStorage.md
span_panel/client/docs/BodySetCircuitStateApiV1CircuitsCircuitIdPost.md
span_panel/client/docs/BooleanIn.md
span_panel/client/docs/Branch.md
span_panel/client/docs/Circuit.md
span_panel/client/docs/CircuitNameIn.md
span_panel/client/docs/CircuitsOut.md
span_panel/client/docs/Client.md
span_panel/client/docs/Clients.md
span_panel/client/docs/DefaultApi.md
span_panel/client/docs/DoorState.md
span_panel/client/docs/FeedthroughEnergy.md
span_panel/client/docs/HTTPValidationError.md
span_panel/client/docs/IslandingState.md
span_panel/client/docs/MainMeterEnergy.md
span_panel/client/docs/NetworkStatus.md
span_panel/client/docs/NiceToHaveThreshold.md
span_panel/client/docs/PanelMeter.md
span_panel/client/docs/PanelPower.md
span_panel/client/docs/PanelState.md
span_panel/client/docs/Priority.md
span_panel/client/docs/PriorityIn.md
span_panel/client/docs/RelayState.md
span_panel/client/docs/RelayStateIn.md
span_panel/client/docs/RelayStateOut.md
span_panel/client/docs/SoftwareStatus.md
span_panel/client/docs/StateOfEnergy.md
span_panel/client/docs/StatusOut.md
span_panel/client/docs/SystemStatus.md
span_panel/client/docs/ValidationError.md
span_panel/client/docs/WifiAccessPoint.md
span_panel/client/docs/WifiConnectIn.md
span_panel/client/docs/WifiConnectOut.md
span_panel/client/docs/WifiScanOut.md
span_panel-0.2.1.dist-info/METADATA
span_panel-0.2.1.dist-info/WHEEL
span_panel-0.2.1.dist-info/entry_points.txt
span_panel-0.2.1.dist-info/RECORD
